binaryconv/__init__.py
binaryconv/convertbin.py
binaryconv/sysm.py
binaryconv-0.0.5.dist-info/METADATA
binaryconv-0.0.5.dist-info/WHEEL
binaryconv-0.0.5.dist-info/licenses/LICENSE
binaryconv-0.0.5.dist-info/RECORD
